human_autoclicker/__init__.py
human_autoclicker/human_autoclicker.py
human_autoclicker/human_autoclicker_gui.py
human_autoclicker-0.1.1.dist-info/METADATA
human_autoclicker-0.1.1.dist-info/WHEEL
human_autoclicker-0.1.1.dist-info/entry_points.txt
human_autoclicker-0.1.1.dist-info/top_level.txt
human_autoclicker-0.1.1.dist-info/RECORD
