Metadata-Version: 2.1
Name: human-autoclicker
Version: 0.1.1
Summary: A simple auto clicker with GUI
Home-page: https://github.com/will-abb/click-bot
Author: Will Bosch-Bello
Author-email: williamsbosch@gmail.com
License: UNKNOWN
Platform: UNKNOWN
Classifier: Programming Language :: Python :: 3
Classifier: License :: OSI Approved :: MIT License
Classifier: Operating System :: OS Independent
Requires-Python: >=3.6
Requires-Dist: markdown
Requires-Dist: pyautogui
Requires-Dist: pynput
Requires-Dist: tkhtmlview
